{"chunk_definitions":[{"row":27,"row_count":1,"visible":true,"expansion_state":0,"options":{"engine":"r","label":"setup","include":false},"document_id":"A4FB976D","chunk_id":"csetup_chunk","chunk_label":"setup"},{"row":35,"row_count":1,"visible":true,"expansion_state":0,"options":{"engine":"r","label":"DeerAP","echo":false,"fig.cap":"Example of 'ageprior' distribution in a red deer population","out.width":"90%"},"document_id":"A4FB976D","chunk_id":"cwgxwgc9b0a2e","chunk_label":"DeerAP"}],"doc_write_time":1602830292,"working_dir":null,"default_chunk_options":{"echo":true,"fig.height":4.0,"fig.width":6.0,"fig.pos":"ht!"},"chunk_rendered_width":617}